odoo/addons/sale_order_packaging_import/README.rst
odoo/addons/sale_order_packaging_import/__init__.py
odoo/addons/sale_order_packaging_import/__manifest__.py
odoo/addons/sale_order_packaging_import/i18n/es.po
odoo/addons/sale_order_packaging_import/i18n/sale_order_packaging_import.pot
odoo/addons/sale_order_packaging_import/models/__init__.py
odoo/addons/sale_order_packaging_import/models/business_document_import.py
odoo/addons/sale_order_packaging_import/readme/CONTRIBUTORS.rst
odoo/addons/sale_order_packaging_import/readme/DESCRIPTION.rst
odoo/addons/sale_order_packaging_import/static/description/icon.png
odoo/addons/sale_order_packaging_import/static/description/index.html
odoo/addons/sale_order_packaging_import/tests/__init__.py
odoo/addons/sale_order_packaging_import/tests/test_order_line_packaging_import.py
odoo/addons/sale_order_packaging_import/wizard/__init__.py
odoo/addons/sale_order_packaging_import/wizard/sale_order_import.py
odoo14_addon_sale_order_packaging_import-14.0.1.1.1.dist-info/METADATA
odoo14_addon_sale_order_packaging_import-14.0.1.1.1.dist-info/WHEEL
odoo14_addon_sale_order_packaging_import-14.0.1.1.1.dist-info/top_level.txt
odoo14_addon_sale_order_packaging_import-14.0.1.1.1.dist-info/RECORD
